Metadata-Version: 2.1
Name: papermerge-meta-plugin-ard-zdf-deutschlandradio
Version: 1.0.0
Summary: metadata extractor plugin for ARD ZDF Rundfunkbeiträge data extraction.
Home-page: https://github.com/papermerge/papermerge-meta-plugin-ard-zdf-deutschlandradio
Author: Eugen Ciur
Author-email: eugen@papermerge.com
License: Apache 2.0 License
Keywords: metadata,papermerge,plugin,receipts
Platform: UNKNOWN
Classifier: Programming Language :: Python :: 3
Classifier: License :: OSI Approved :: Apache Software License
Classifier: Operating System :: OS Independent
Requires-Python: >=3.7
